moveread/dfy_connector/__init__.py
moveread/dfy_connector/__init__.pyi
moveread/dfy_connector/pull.py
moveread/dfy_connector/push.py
moveread/dfy_connector/scripts/__init__.py
moveread/dfy_connector/scripts/pull.py
moveread/dfy_connector/scripts/push.py
moveread_dfy_connector-0.2.7.dist-info/METADATA
moveread_dfy_connector-0.2.7.dist-info/WHEEL
moveread_dfy_connector-0.2.7.dist-info/entry_points.txt
moveread_dfy_connector-0.2.7.dist-info/top_level.txt
moveread_dfy_connector-0.2.7.dist-info/RECORD
